{
  "aor": 0.00027471631205673765,
  "aqi": 0.014111819361702128,
  "bids_meta": {
    "RepetitionTime": 2.0,
    "SliceTiming": [
      0.0,
      0.0541,
      0.1082,
      0.1623,
      0.2164,
      0.2705,
      0.3246,
      0.3787,
      0.4328,
      0.4869,
      0.541,
      0.5951,
      0.6492,
      0.7033,
      0.7574,
      0.8115,
      0.8656,
      0.9197,
      0.9738,
      1.0279,
      1.082,
      1.1361,
      1.1902,
      1.2443,
      1.2984,
      1.3525,
      1.4066,
      1.4607,
      1.5148,
      1.5689,
      1.623,
      1.6771,
      1.7312,
      1.7853,
      1.8394,
      1.8935,
      1.9476
    ],
    "TaskName": "identify",
    "dataset": "ds003831",
    "modality": "bold",
    "subject_id": "010",
    "task_id": "identify1"
  },
  "dummy_trs": 0,
  "dvars_nstd": 28.612733813879004,
  "dvars_std": 1.17196970380783,
  "dvars_vstd": 0.9285317833451956,
  "efc": 0.41701007196079504,
  "fber": 122300.1328125,
  "fd_mean": 0.12112006826604117,
  "fd_num": 9,
  "fd_perc": 3.1914893617021276,
  "fwhm_avg": 1.8395655555555557,
  "fwhm_x": 1.7922666666666667,
  "fwhm_y": 1.9524533333333334,
  "fwhm_z": 1.7739766666666668,
  "gcor": 0.0419936,
  "gsr_x": -0.013699975796043873,
  "gsr_y": 0.006404095329344273,
  "provenance": {
    "md5sum": "b56ba6c4d1459cfc0f93447474867db4",
    "settings": {
      "fd_thres": 0.2,
      "testing": false
    },
    "software": "mriqc",
    "version": "23.0.0",
    "webapi_port": null,
    "webapi_url": "https://mriqc.nimh.nih.gov/api/v1"
  },
  "size_t": 282,
  "size_x": 80,
  "size_y": 80,
  "size_z": 37,
  "snr": 5.542106569510052,
  "spacing_tr": 2.0,
  "spacing_x": 3.0,
  "spacing_y": 3.0,
  "spacing_z": 3.0,
  "summary_bg_k": 97.10648465382125,
  "summary_bg_mad": 3.5464422412467638,
  "summary_bg_mean": 16.35909080505371,
  "summary_bg_median": 2.964749336242676,
  "summary_bg_n": 160333.0,
  "summary_bg_p05": 0.2228414297103882,
  "summary_bg_p95": 72.05593261718745,
  "summary_bg_stdv": 45.79185485839844,
  "summary_fg_k": 3.845628930044165,
  "summary_fg_mad": 164.0266250326078,
  "summary_fg_mean": 1066.5592041015625,
  "summary_fg_median": 1045.64990234375,
  "summary_fg_n": 36287.0,
  "summary_fg_p05": 821.3747009277344,
  "summary_fg_p95": 1379.3163085937497,
  "summary_fg_stdv": 188.67112731933594,
  "tsnr": 49.38271713256836
}