{
  "aor": 0.002555032258064516,
  "aqi": 0.008916150064516128,
  "bids_meta": {
    "RepetitionTime": 2.0,
    "SliceTiming": [
      0.0,
      0.0541,
      0.1082,
      0.1623,
      0.2164,
      0.2705,
      0.3246,
      0.3787,
      0.4328,
      0.4869,
      0.541,
      0.5951,
      0.6492,
      0.7033,
      0.7574,
      0.8115,
      0.8656,
      0.9197,
      0.9738,
      1.0279,
      1.082,
      1.1361,
      1.1902,
      1.2443,
      1.2984,
      1.3525,
      1.4066,
      1.4607,
      1.5148,
      1.5689,
      1.623,
      1.6771,
      1.7312,
      1.7853,
      1.8394,
      1.8935,
      1.9476
    ],
    "TaskName": "modulate",
    "dataset": "ds003831",
    "modality": "bold",
    "subject_id": "043",
    "task_id": "modulate1"
  },
  "dummy_trs": 0,
  "dvars_nstd": 23.084110902071178,
  "dvars_std": 1.1444331099676366,
  "dvars_vstd": 1.0314614685760521,
  "efc": 0.4330934422189309,
  "fber": 142310.609375,
  "fd_mean": 0.15013765933140263,
  "fd_num": 58,
  "fd_perc": 18.70967741935484,
  "fwhm_avg": 1.9422733333333335,
  "fwhm_x": 1.9164533333333333,
  "fwhm_y": 2.15295,
  "fwhm_z": 1.7574166666666666,
  "gcor": 0.0615423,
  "gsr_x": -0.01607299968600273,
  "gsr_y": 0.011442121118307114,
  "provenance": {
    "md5sum": "e26cefb240aaa68d3fa2707f6f590ac2",
    "settings": {
      "fd_thres": 0.2,
      "testing": false
    },
    "software": "mriqc",
    "version": "23.0.0",
    "webapi_port": null,
    "webapi_url": "https://mriqc.nimh.nih.gov/api/v1"
  },
  "size_t": 310,
  "size_x": 80,
  "size_y": 80,
  "size_z": 37,
  "snr": 4.842242538067935,
  "spacing_tr": 2.0,
  "spacing_x": 3.0,
  "spacing_y": 3.0,
  "spacing_z": 3.0,
  "summary_bg_k": 25.502846546338656,
  "summary_bg_mad": 2.8704090993841156,
  "summary_bg_mean": 19.13582420349121,
  "summary_bg_median": 2.368903636932373,
  "summary_bg_n": 157736.0,
  "summary_bg_p05": 0.15195447951555252,
  "summary_bg_p95": 110.78686904907227,
  "summary_bg_stdv": 47.855567932128906,
  "summary_fg_k": 5.8950491357282715,
  "summary_fg_mad": 144.95386687865116,
  "summary_fg_mean": 953.3718872070312,
  "summary_fg_median": 925.26220703125,
  "summary_fg_n": 37744.0,
  "summary_fg_p05": 719.5019134521484,
  "summary_fg_p95": 1261.1967407226562,
  "summary_fg_stdv": 191.0788116455078,
  "tsnr": 54.13998794555664
}